toroidal/__init__.py
toroidal/models.py
toroidal-0.0.1.post2.dist-info/METADATA
toroidal-0.0.1.post2.dist-info/WHEEL
toroidal-0.0.1.post2.dist-info/top_level.txt
toroidal-0.0.1.post2.dist-info/RECORD
