Metadata-Version: 2.1
Name: toroidal
Version: 0.0.1.post2
Summary: Toroidal - Lightweight Transformers for PyTorch
Home-page: https://github.com/mathinf/toroidal/
Author: MathInf GmbH
License: UNKNOWN
Platform: UNKNOWN
Requires-Dist: torch
